synthesis/alu_gate.v
/* Generated by Yosys 0.33 (git sha1 2584903a060) */

module alu_8bit(A, B, opcode, result, carry, zero);
  wire _000_;
  wire _001_;
  wire _002_;
  wire _003_;
  wire _004_;
  wire _005_;
  wire _006_;
  wire [2:0] _007_;
  wire _008_;
  wire _009_;
  wire [3:0] _010_;
  wire [1:0] _011_;
  wire [3:0] _012_;
  wire [1:0] _013_;
  wire [3:0] _014_;
  wire [1:0] _015_;
  wire [3:0] _016_;
  wire [1:0] _017_;
  wire [3:0] _018_;
  wire [1:0] _019_;
  wire [3:0] _020_;
  wire [1:0] _021_;
  wire [3:0] _022_;
  wire [1:0] _023_;
  wire [3:0] _024_;
  wire [1:0] _025_;
  wire [3:0] _026_;
  wire [1:0] _027_;
  wire [3:0] _028_;
  wire [1:0] _029_;
  wire _030_;
  wire _031_;
  wire _032_;
  wire _033_;
  wire _034_;
  wire _035_;
  wire _036_;
  wire _037_;
  wire _038_;
  wire [2:0] _039_;
  wire [2:0] _040_;
  wire [2:0] _041_;
  wire _042_;
  wire [63:0] _043_;
  wire [63:0] _044_;
  wire [7:0] _045_;
  wire [7:0] _046_;
  wire [8:0] _047_;
  wire _048_;
  wire _049_;
  wire [8:0] _050_;
  wire [8:0] _051_;
  wire [8:0] _052_;
  wire [8:0] _053_;
  wire _054_;
  wire _055_;
  wire _056_;
  wire _057_;
  wire _058_;
  wire _059_;
  wire _060_;
  wire _061_;
  wire _062_;
  wire _063_;
  wire _064_;
  wire _065_;
  wire _066_;
  wire _067_;
  wire _068_;
  wire _069_;
  wire _070_;
  wire _071_;
  wire _072_;
  wire _073_;
  wire _074_;
  wire _075_;
  wire _076_;
  wire _077_;
  wire _078_;
  wire _079_;
  wire _080_;
  wire _081_;
  wire _082_;
  wire _083_;
  wire _084_;
  wire _085_;
  wire _086_;
  wire _087_;
  wire _088_;
  wire _089_;
  wire _090_;
  wire _091_;
  input [7:0] A;
  wire [7:0] A;
  input [7:0] B;
  wire [7:0] B;
  output carry;
  wire carry;
  input [2:0] opcode;
  wire [2:0] opcode;
  output [7:0] result;
  wire [7:0] result;
  output zero;
  wire zero;
  assign _000_ = ~opcode[2];
  assign _001_ = ~opcode[1];
  assign _002_ = ~opcode[0];
  assign _043_[48] = ~_052_[0];
  assign _039_[1] = ~_051_[8];
  assign _032_ = _003_ | opcode[2];
  assign _033_ = _004_ | _000_;
  assign _034_ = _005_ | _000_;
  assign _003_ = _002_ | opcode[1];
  assign _035_ = _003_ | _000_;
  assign _006_ = opcode[0] | opcode[1];
  assign _036_ = _006_ | _000_;
  assign _004_ = _002_ | _001_;
  assign _037_ = _004_ | opcode[2];
  assign _005_ = opcode[0] | _001_;
  assign _038_ = _005_ | opcode[2];
  assign _041_[0] = _008_ | _007_[2];
  assign _042_ = _040_[1] | _040_[2];
  assign _009_ = _041_[0] | _041_[1];
  assign _048_ = _009_ | _041_[2];
  assign _010_[1] = _044_[23] | _044_[31];
  assign _010_[2] = _044_[39] | _044_[47];
  assign _010_[3] = _044_[55] | _044_[63];
  assign _011_[0] = _044_[15] | _010_[1];
  assign _011_[1] = _010_[2] | _010_[3];
  assign _046_[7] = _011_[0] | _011_[1];
  assign _012_[0] = _044_[6] | _044_[14];
  assign _012_[1] = _044_[22] | _044_[30];
  assign _012_[2] = _044_[38] | _044_[46];
  assign _012_[3] = _044_[54] | _044_[62];
  assign _013_[0] = _012_[0] | _012_[1];
  assign _013_[1] = _012_[2] | _012_[3];
  assign _046_[6] = _013_[0] | _013_[1];
  assign _014_[0] = _044_[5] | _044_[13];
  assign _014_[1] = _044_[21] | _044_[29];
  assign _014_[2] = _044_[37] | _044_[45];
  assign _014_[3] = _044_[53] | _044_[61];
  assign _015_[0] = _014_[0] | _014_[1];
  assign _015_[1] = _014_[2] | _014_[3];
  assign _046_[5] = _015_[0] | _015_[1];
  assign _016_[0] = _044_[4] | _044_[12];
  assign _016_[1] = _044_[20] | _044_[28];
  assign _016_[2] = _044_[36] | _044_[44];
  assign _016_[3] = _044_[52] | _044_[60];
  assign _017_[0] = _016_[0] | _016_[1];
  assign _017_[1] = _016_[2] | _016_[3];
  assign _046_[4] = _017_[0] | _017_[1];
  assign _018_[0] = _044_[3] | _044_[11];
  assign _018_[1] = _044_[19] | _044_[27];
  assign _018_[2] = _044_[35] | _044_[43];
  assign _018_[3] = _044_[51] | _044_[59];
  assign _019_[0] = _018_[0] | _018_[1];
  assign _019_[1] = _018_[2] | _018_[3];
  assign _046_[3] = _019_[0] | _019_[1];
  assign _020_[0] = _044_[2] | _044_[10];
  assign _020_[1] = _044_[18] | _044_[26];
  assign _020_[2] = _044_[34] | _044_[42];
  assign _020_[3] = _044_[50] | _044_[58];
  assign _021_[0] = _020_[0] | _020_[1];
  assign _021_[1] = _020_[2] | _020_[3];
  assign _046_[2] = _021_[0] | _021_[1];
  assign _022_[0] = _044_[1] | _044_[9];
  assign _022_[1] = _044_[17] | _044_[25];
  assign _022_[2] = _044_[33] | _044_[41];
  assign _022_[3] = _044_[49] | _044_[57];
  assign _023_[0] = _022_[0] | _022_[1];
  assign _023_[1] = _022_[2] | _022_[3];
  assign _046_[1] = _023_[0] | _023_[1];
  assign _024_[1] = _044_[16] | _044_[24];
  assign _024_[2] = _044_[32] | _044_[40];
  assign _024_[3] = _044_[48] | _044_[56];
  assign _025_[0] = _044_[0] | _024_[1];
  assign _025_[1] = _024_[2] | _024_[3];
  assign _046_[0] = _025_[0] | _025_[1];
  assign _007_[0] = _045_[0] | _045_[1];
  assign _007_[1] = _045_[2] | _045_[3];
  assign _007_[2] = _045_[4] | _045_[5];
  assign _026_[3] = _041_[1] | _041_[2];
  assign _008_ = _007_[0] | _007_[1];
  assign _027_[1] = _007_[2] | _026_[3];
  assign _049_ = _008_ | _027_[1];
  assign _028_[0] = result[0] | result[1];
  assign _028_[1] = result[2] | result[3];
  assign _028_[2] = result[4] | result[5];
  assign _028_[3] = result[6] | result[7];
  assign _029_[0] = _028_[0] | _028_[1];
  assign _029_[1] = _028_[2] | _028_[3];
  assign _030_ = _029_[0] | _029_[1];
  assign _031_ = _006_ | opcode[2];
  assign zero = ~_030_;
  assign _041_[1] = ~_032_;
  assign _041_[2] = ~_031_;
  assign _045_[0] = ~_033_;
  assign _045_[1] = ~_034_;
  assign _045_[2] = ~_035_;
  assign _045_[3] = ~_036_;
  assign _045_[4] = ~_037_;
  assign _045_[5] = ~_038_;
  assign carry = _048_ ? _042_ : 1'hx;
  assign result[0] = _049_ ? _046_[0] : 1'hx;
  assign result[1] = _049_ ? _046_[1] : 1'hx;
  assign result[2] = _049_ ? _046_[2] : 1'hx;
  assign result[3] = _049_ ? _046_[3] : 1'hx;
  assign result[4] = _049_ ? _046_[4] : 1'hx;
  assign result[5] = _049_ ? _046_[5] : 1'hx;
  assign result[6] = _049_ ? _046_[6] : 1'hx;
  assign result[7] = _049_ ? _046_[7] : 1'hx;
  assign _043_[16] = ~A[0];
  assign _043_[17] = ~A[1];
  assign _043_[18] = ~A[2];
  assign _043_[19] = ~A[3];
  assign _043_[20] = ~A[4];
  assign _043_[21] = ~A[5];
  assign _043_[22] = ~A[6];
  assign _043_[23] = ~A[7];
  assign _050_[0] = ~B[0];
  assign _050_[1] = ~B[1];
  assign _050_[2] = ~B[2];
  assign _050_[3] = ~B[3];
  assign _050_[4] = ~B[4];
  assign _050_[5] = ~B[5];
  assign _050_[6] = ~B[6];
  assign _050_[7] = ~B[7];
  assign _043_[32] = A[0] | B[0];
  assign _043_[33] = A[1] | B[1];
  assign _043_[34] = A[2] | B[2];
  assign _043_[35] = A[3] | B[3];
  assign _043_[36] = A[4] | B[4];
  assign _043_[37] = A[5] | B[5];
  assign _043_[38] = A[6] | B[6];
  assign _043_[39] = A[7] | B[7];
  assign _040_[2] = _039_[2] & _041_[2];
  assign _040_[1] = _039_[1] & _041_[1];
  assign _044_[56] = _043_[56] & _041_[2];
  assign _044_[57] = _043_[57] & _041_[2];
  assign _044_[58] = _043_[58] & _041_[2];
  assign _044_[59] = _043_[59] & _041_[2];
  assign _044_[60] = _043_[60] & _041_[2];
  assign _044_[61] = _043_[61] & _041_[2];
  assign _044_[62] = _043_[62] & _041_[2];
  assign _044_[63] = _043_[63] & _041_[2];
  assign _044_[48] = _043_[48] & _041_[1];
  assign _044_[49] = _043_[49] & _041_[1];
  assign _044_[50] = _043_[50] & _041_[1];
  assign _044_[51] = _043_[51] & _041_[1];
  assign _044_[52] = _043_[52] & _041_[1];
  assign _044_[53] = _043_[53] & _041_[1];
  assign _044_[54] = _043_[54] & _041_[1];
  assign _044_[55] = _043_[55] & _041_[1];
  assign _044_[40] = _043_[40] & _045_[5];
  assign _044_[41] = _043_[41] & _045_[5];
  assign _044_[42] = _043_[42] & _045_[5];
  assign _044_[43] = _043_[43] & _045_[5];
  assign _044_[44] = _043_[44] & _045_[5];
  assign _044_[45] = _043_[45] & _045_[5];
  assign _044_[46] = _043_[46] & _045_[5];
  assign _044_[47] = _043_[47] & _045_[5];
  assign _044_[32] = _043_[32] & _045_[4];
  assign _044_[33] = _043_[33] & _045_[4];
  assign _044_[34] = _043_[34] & _045_[4];
  assign _044_[35] = _043_[35] & _045_[4];
  assign _044_[36] = _043_[36] & _045_[4];
  assign _044_[37] = _043_[37] & _045_[4];
  assign _044_[38] = _043_[38] & _045_[4];
  assign _044_[39] = _043_[39] & _045_[4];
  assign _044_[24] = _043_[56] & _045_[3];
  assign _044_[25] = _043_[25] & _045_[3];
  assign _044_[26] = _043_[26] & _045_[3];
  assign _044_[27] = _043_[27] & _045_[3];
  assign _044_[28] = _043_[28] & _045_[3];
  assign _044_[29] = _043_[29] & _045_[3];
  assign _044_[30] = _043_[30] & _045_[3];
  assign _044_[31] = _043_[31] & _045_[3];
  assign _044_[16] = _043_[16] & _045_[2];
  assign _044_[17] = _043_[17] & _045_[2];
  assign _044_[18] = _043_[18] & _045_[2];
  assign _044_[19] = _043_[19] & _045_[2];
  assign _044_[20] = _043_[20] & _045_[2];
  assign _044_[21] = _043_[21] & _045_[2];
  assign _044_[22] = _043_[22] & _045_[2];
  assign _044_[23] = _043_[23] & _045_[2];
  assign _044_[9] = A[0] & _045_[1];
  assign _044_[10] = A[1] & _045_[1];
  assign _044_[11] = A[2] & _045_[1];
  assign _044_[12] = A[3] & _045_[1];
  assign _044_[13] = A[4] & _045_[1];
  assign _044_[14] = A[5] & _045_[1];
  assign _044_[15] = A[6] & _045_[1];
  assign _044_[0] = A[1] & _045_[0];
  assign _044_[1] = A[2] & _045_[0];
  assign _044_[2] = A[3] & _045_[0];
  assign _044_[3] = A[4] & _045_[0];
  assign _044_[4] = A[5] & _045_[0];
  assign _044_[5] = A[6] & _045_[0];
  assign _044_[6] = A[7] & _045_[0];
  assign _043_[57] = _043_[25] ^ _043_[40];
  assign _043_[58] = _043_[26] ^ _047_[1];
  assign _043_[59] = _043_[27] ^ _047_[2];
  assign _043_[60] = _043_[28] ^ _047_[3];
  assign _043_[61] = _043_[29] ^ _047_[4];
  assign _043_[62] = _043_[30] ^ _047_[5];
  assign _043_[63] = _043_[31] ^ _047_[6];
  assign _043_[56] = B[0] ^ A[0];
  assign _043_[25] = B[1] ^ A[1];
  assign _043_[26] = B[2] ^ A[2];
  assign _043_[27] = B[3] ^ A[3];
  assign _043_[28] = B[4] ^ A[4];
  assign _043_[29] = B[5] ^ A[5];
  assign _043_[30] = B[6] ^ A[6];
  assign _043_[31] = B[7] ^ A[7];
  assign _043_[40] = B[0] & A[0];
  assign _043_[41] = B[1] & A[1];
  assign _043_[42] = B[2] & A[2];
  assign _043_[43] = B[3] & A[3];
  assign _043_[44] = B[4] & A[4];
  assign _043_[45] = B[5] & A[5];
  assign _043_[46] = B[6] & A[6];
  assign _043_[47] = B[7] & A[7];
  assign _043_[49] = _052_[1] ^ _051_[0];
  assign _043_[50] = _052_[2] ^ _051_[1];
  assign _043_[51] = _052_[3] ^ _051_[2];
  assign _043_[52] = _052_[4] ^ _051_[3];
  assign _043_[53] = _052_[5] ^ _051_[4];
  assign _043_[54] = _052_[6] ^ _051_[5];
  assign _043_[55] = _052_[7] ^ _051_[6];
  assign _052_[0] = A[0] ^ _050_[0];
  assign _052_[1] = A[1] ^ _050_[1];
  assign _052_[2] = A[2] ^ _050_[2];
  assign _052_[3] = A[3] ^ _050_[3];
  assign _052_[4] = A[4] ^ _050_[4];
  assign _052_[5] = A[5] ^ _050_[5];
  assign _052_[6] = A[6] ^ _050_[6];
  assign _052_[7] = A[7] ^ _050_[7];
  assign _053_[0] = A[0] & _050_[0];
  assign _053_[1] = A[1] & _050_[1];
  assign _053_[2] = A[2] & _050_[2];
  assign _053_[3] = A[3] & _050_[3];
  assign _053_[4] = A[4] & _050_[4];
  assign _053_[5] = A[5] & _050_[5];
  assign _053_[6] = A[6] & _050_[6];
  assign _053_[7] = A[7] & _050_[7];
  assign _054_ = _043_[25] & _043_[40];
  assign _055_ = _043_[27] & _043_[42];
  assign _056_ = _043_[29] & _043_[44];
  assign _057_ = _043_[31] & _043_[46];
  assign _058_ = _061_ & _047_[1];
  assign _059_ = _063_ & _070_;
  assign _060_ = _064_ & _047_[3];
  assign _061_ = _043_[27] & _043_[26];
  assign _062_ = _043_[29] & _043_[28];
  assign _063_ = _043_[31] & _043_[30];
  assign _064_ = _063_ & _062_;
  assign _065_ = _062_ & _047_[3];
  assign _066_ = _043_[26] & _047_[1];
  assign _067_ = _043_[28] & _047_[3];
  assign _068_ = _043_[30] & _047_[5];
  assign _047_[1] = _043_[41] | _054_;
  assign _069_ = _043_[43] | _055_;
  assign _070_ = _043_[45] | _056_;
  assign _071_ = _043_[47] | _057_;
  assign _047_[3] = _069_ | _058_;
  assign _072_ = _071_ | _059_;
  assign _039_[2] = _072_ | _060_;
  assign _047_[5] = _070_ | _065_;
  assign _047_[2] = _043_[42] | _066_;
  assign _047_[4] = _043_[44] | _067_;
  assign _047_[6] = _043_[46] | _068_;
  assign _073_ = _052_[1] & _051_[0];
  assign _074_ = _052_[3] & _053_[2];
  assign _075_ = _052_[5] & _053_[4];
  assign _076_ = _052_[7] & _053_[6];
  assign _077_ = _080_ & _051_[1];
  assign _078_ = _082_ & _089_;
  assign _079_ = _083_ & _051_[3];
  assign _080_ = _052_[3] & _052_[2];
  assign _081_ = _052_[5] & _052_[4];
  assign _082_ = _052_[7] & _052_[6];
  assign _083_ = _082_ & _081_;
  assign _084_ = _081_ & _051_[3];
  assign _085_ = _052_[2] & _051_[1];
  assign _086_ = _052_[4] & _051_[3];
  assign _087_ = _052_[6] & _051_[5];
  assign _051_[0] = _053_[0] | _052_[0];
  assign _051_[1] = _053_[1] | _073_;
  assign _088_ = _053_[3] | _074_;
  assign _089_ = _053_[5] | _075_;
  assign _090_ = _053_[7] | _076_;
  assign _051_[3] = _088_ | _077_;
  assign _091_ = _090_ | _078_;
  assign _051_[8] = _091_ | _079_;
  assign _051_[5] = _089_ | _084_;
  assign _051_[2] = _053_[2] | _085_;
  assign _051_[4] = _053_[4] | _086_;
  assign _051_[6] = _053_[6] | _087_;
  assign _010_[0] = _044_[15];
  assign _024_[0] = _044_[0];
  assign _026_[2:0] = _007_;
  assign _027_[0] = _008_;
  assign _039_[0] = 1'h0;
  assign _040_[0] = 1'h0;
  assign { _043_[24], _043_[15:0] } = { _043_[56], A[6:0], 2'h0, A[7:1] };
  assign _044_[8:7] = 2'h0;
  assign _045_[7:6] = _041_[2:1];
  assign { _047_[8:7], _047_[0] } = { 1'h0, _039_[2], _043_[40] };
  assign _050_[8] = 1'h1;
  assign _051_[7] = _051_[8];
  assign _052_[8] = 1'h1;
  assign _053_[8] = 1'h0;
endmodule

sim/alu_tb.v
`timescale 1ns/1ps

module alu_tb;

reg  [7:0] A;
reg  [7:0] B;
reg  [2:0] opcode;

wire [7:0] result;
wire       carry;
wire       zero;

alu_8bit uut (
    .A(A),
    .B(B),
    .opcode(opcode),
    .result(result),
    .carry(carry),
    .zero(zero)
);

initial begin

    $dumpfile("alu.vcd");
    $dumpvars(0, alu_tb);

    // ADD
    A = 8'd10;
    B = 8'd5;
    opcode = 3'b000;
    #10;

    // SUB
    A = 8'd10;
    B = 8'd5;
    opcode = 3'b001;
    #10;

    // AND
    A = 8'b10101010;
    B = 8'b11001100;
    opcode = 3'b010;
    #10;

    // OR
    opcode = 3'b011;
    #10;

    // XOR
    opcode = 3'b100;
    #10;

    // NOT
    opcode = 3'b101;
    #10;

    // SHIFT LEFT
    A = 8'b00001111;
    opcode = 3'b110;
    #10;

    // SHIFT RIGHT
    A = 8'b11110000;
    opcode = 3'b111;
    #10;

    $finish;

end

endmodule

alu.vcd
$date
	Sun Aug  9 18:07:05 2026
$end
$version
	Icarus Verilog
$end
$timescale
	1ps
$end
$scope module alu_tb $end
$var wire 1 ! zero $end
$var wire 8 " result [7:0] $end
$var wire 1 # carry $end
$var reg 8 $ A [7:0] $end
$var reg 8 % B [7:0] $end
$var reg 3 & opcode [2:0] $end
$scope module uut $end
$var wire 8 ' A [7:0] $end
$var wire 8 ( B [7:0] $end
$var wire 1 ) _000_ $end
$var wire 1 * _001_ $end
$var wire 1 + _002_ $end
$var wire 1 , _003_ $end
$var wire 1 - _004_ $end
$var wire 1 . _005_ $end
$var wire 1 / _006_ $end
$var wire 1 0 _008_ $end
$var wire 1 1 _009_ $end
$var wire 1 2 _030_ $end
$var wire 1 3 _031_ $end
$var wire 1 4 _032_ $end
$var wire 1 5 _033_ $end
$var wire 1 6 _034_ $end
$var wire 1 7 _035_ $end
$var wire 1 8 _036_ $end
$var wire 1 9 _037_ $end
$var wire 1 : _038_ $end
$var wire 1 ; _042_ $end
$var wire 1 < _048_ $end
$var wire 1 = _049_ $end
$var wire 1 > _054_ $end
$var wire 1 ? _055_ $end
$var wire 1 @ _056_ $end
$var wire 1 A _057_ $end
$var wire 1 B _058_ $end
$var wire 1 C _059_ $end
$var wire 1 D _060_ $end
$var wire 1 E _061_ $end
$var wire 1 F _062_ $end
$var wire 1 G _063_ $end
$var wire 1 H _064_ $end
$var wire 1 I _065_ $end
$var wire 1 J _066_ $end
$var wire 1 K _067_ $end
$var wire 1 L _068_ $end
$var wire 1 M _069_ $end
$var wire 1 N _070_ $end
$var wire 1 O _071_ $end
$var wire 1 P _072_ $end
$var wire 1 Q _073_ $end
$var wire 1 R _074_ $end
$var wire 1 S _075_ $end
$var wire 1 T _076_ $end
$var wire 1 U _077_ $end
$var wire 1 V _078_ $end
$var wire 1 W _079_ $end
$var wire 1 X _080_ $end
$var wire 1 Y _081_ $end
$var wire 1 Z _082_ $end
$var wire 1 [ _083_ $end
$var wire 1 \ _084_ $end
$var wire 1 ] _085_ $end
$var wire 1 ^ _086_ $end
$var wire 1 _ _087_ $end
$var wire 1 ` _088_ $end
$var wire 1 a _089_ $end
$var wire 1 b _090_ $end
$var wire 1 c _091_ $end
$var wire 3 d opcode [2:0] $end
$var wire 1 ! zero $end
$var wire 8 e result [7:0] $end
$var wire 1 # carry $end
$var wire 9 f _053_ [8:0] $end
$var wire 9 g _052_ [8:0] $end
$var wire 9 h _051_ [8:0] $end
$var wire 9 i _050_ [8:0] $end
$var wire 9 j _047_ [8:0] $end
$var wire 8 k _046_ [7:0] $end
$var wire 8 l _045_ [7:0] $end
$var wire 64 m _044_ [63:0] $end
$var wire 64 n _043_ [63:0] $end
$var wire 3 o _041_ [2:0] $end
$var wire 3 p _040_ [2:0] $end
$var wire 3 q _039_ [2:0] $end
$var wire 2 r _029_ [1:0] $end
$var wire 4 s _028_ [3:0] $end
$var wire 2 t _027_ [1:0] $end
$var wire 4 u _026_ [3:0] $end
$var wire 2 v _025_ [1:0] $end
$var wire 4 w _024_ [3:0] $end
$var wire 2 x _023_ [1:0] $end
$var wire 4 y _022_ [3:0] $end
$var wire 2 z _021_ [1:0] $end
$var wire 4 { _020_ [3:0] $end
$var wire 2 | _019_ [1:0] $end
$var wire 4 } _018_ [3:0] $end
$var wire 2 ~ _017_ [1:0] $end
$var wire 4 !" _016_ [3:0] $end
$var wire 2 "" _015_ [1:0] $end
$var wire 4 #" _014_ [3:0] $end
$var wire 2 $" _013_ [1:0] $end
$var wire 4 %" _012_ [3:0] $end
$var wire 2 &" _011_ [1:0] $end
$var wire 4 '" _010_ [3:0] $end
$var wire 3 (" _007_ [2:0] $end
$upscope $end
$upscope $end
$enddefinitions $end
$comment Show the parameter values. $end
$dumpall
$end
#0
$dumpvars
b0 ("
b0 '"
b0 &"
b0 %"
b0 $"
b0 #"
b0 ""
b0 !"
b0 ~
b1000 }
b10 |
b1000 {
b10 z
b1000 y
b10 x
b1000 w
b10 v
b1000 u
b10 t
b11 s
b1 r
b0 q
b0 p
b100 o
b111100000101000000000000111100001111111101010001010000000101 n
b111100000000000000000000000000000000000000000000000000000000 m
b10000000 l
b1111 k
b0 j
b111111010 i
b111111010 h
b111110000 g
b1010 f
b1111 e
b0 d
0c
0b
0a
1`
1_
1^
0]
1\
1[
1Z
1Y
0X
1W
0V
0U
0T
0S
0R
0Q
0P
0O
0N
0M
0L
0K
0J
0I
0H
0G
0F
1E
0D
0C
0B
0A
0@
0?
0>
1=
1<
0;
1:
19
18
17
16
15
14
03
12
01
00
0/
1.
1-
1,
1+
1*
1)
b101 (
b1010 '
b0 &
b101 %
b1010 $
0#
b1111 "
0!
$end
#10000
0!
12
b1 r
b11 s
b101 k
b101 "
b101 e
b10 v
b0 x
b10 z
b0 |
1=
b1000 w
b0 y
b1000 {
b0 }
b10 t
11
0#
b101000000000000000000000000000000000000000000000000 m
b1000 u
1<
b1000000 l
04
b10 o
0,
13
0+
1/
b1 &
b1 d
#20000
0!
12
b11 r
b1010 s
b10001000 k
b10 &"
b10 |
b10001000 "
b10001000 e
b0 v
b0 z
1=
b100 '"
b100 }
0^
b0 w
b0 {
b10 t
0#
b100 ("
1<
b100010000000000000000000000000000000000000000000 m
b100 u
11
b100011 h
0`
0_
b110 q
0W
b100000 l
b10001000 j
1P
0\
0[
0c
0:
b1 o
0E
1M
1O
0Y
0Z
1a
0b
0.
14
0*
1+
1,
b100110011 i
b110011001 g
b100010 f
b111011011011110100010001110111001100110010101010101010001010101 n
b10 &
b10 d
b11001100 %
b11001100 (
b10101010 $
b10101010 '
#30000
0!
12
b11 r
b1111 s
b11101110 k
0#
b10 $"
b10 ""
b10 z
b10 x
b11101110 "
b11101110 e
1<
b10 &"
b10 |
1=
11
b100 %"
b100 #"
b100 {
b100 y
b100 '"
b100 }
b10 t
b1 o
b1110111000000000000000000000000000000000 m
b100 u
b100 ("
09
b10000 l
0-
1:
0+
1.
b11 &
b11 d
#40000
b1111 s
b1100110 "
b1100110 e
b1100110 k
0#
b0 v
1<
b0 ~
b0 &"
b1 $"
b1 ""
b0 |
b1 z
b1 x
11
b0 w
b0 !"
10
b0 '"
b10 %"
b10 #"
b0 }
b10 {
b10 y
b1 t
b1 o
b1100110000000000000000000000000 m
b10 u
b10 ("
1-
17
08
b1000 l
16
0)
1*
1+
1,
0/
19
1.
b100 &
b100 d
#50000
0!
12
b11 r
0#
b1010101 k
b1111 s
1<
b1 ~
b1 v
11
b1 $"
b0 ""
b1 z
b0 x
b1010101 "
b1010101 e
b10 !"
b10 w
1=
b1 o
b10 %"
b0 #"
b10 {
b0 y
b1 t
10
b10101010000000000000000 m
b10 u
b10 ("
07
b100 l
0,
18
0+
1/
b101 &
b101 d
#60000
0!
12
b11 r
0#
b111 s
1<
b1 |
b1 x
11
b0 $"
b1 ~
b11110 "
b11110 e
b11110 k
b1 }
b1 y
1=
b1 o
b0 %"
b1 !"
b1 t
10
b0 v
b1 z
b0 ""
b0 &"
1^
1\
b1 u
b1 ("
b0 w
b1 {
b0 #"
b0 '"
b10 q
0P
1U
b111111 h
06
b10 l
b1111000000000 m
1G
b1100 j
0O
1]
1X
1Y
0a
0.
17
0*
1+
1,
b100111100 g
b11 f
b1101101101000011000011001100111111000011111100000001111000000111 n
b110 &
b110 d
b1111 $
b1111 '
#70000
0!
12
b11 r
0#
1<
11
b1110 s
1=
b1 o
b1 t
10
b1111000 "
b1111000 e
b1 u
b1 ("
b0 x
b0 z
b1 |
b1 ~
b1 ""
b1 $"
b1111000 k
b100 q
1c
0I
1P
0U
0\
1V
05
b1 l
b0 y
b0 {
b1 }
b1 !"
b1 #"
b1 %"
b0 &"
1E
0K
1F
0G
0M
b11000000 j
1O
1Q
0]
0X
0^
0Y
1_
1Z
b111110011 h
1a
0-
16
b0 '"
0+
1.
b1111000 m
b111000011 g
b110000 f
b1011110000100100110000001111110000111100000011111110000001111000 n
b111 &
b111 d
b11110000 $
b11110000 '
