rtl/alu.v
`timescale 1ns/1ps

module alu_8bit (
    input  [7:0] A,
    input  [7:0] B,
    input  [2:0] opcode,
    output reg [7:0] result,
    output reg       carry,
    output            zero
);

always @(*) begin
    result = 8'b0;
    carry  = 1'b0;

    case (opcode)

        3'b000: begin
            {carry, result} = A + B;
        end

        3'b001: begin
            {carry, result} = A - B;
        end

        3'b010: begin
            result = A & B;
        end

        3'b011: begin
            result = A | B;
        end

        3'b100: begin
            result = A ^ B;
        end

        3'b101: begin
            result = ~A;
        end

        3'b110: begin
            result = A << 1;
        end

        3'b111: begin
            result = A >> 1;
        end

    endcase
end

assign zero = (result == 8'b0);

endmodule

sim/alu_tb.v
`timescale 1ns/1ps

module alu_tb;

reg  [7:0] A;
reg  [7:0] B;
reg  [2:0] opcode;

wire [7:0] result;
wire       carry;
wire       zero;

alu_8bit uut (
    .A(A),
    .B(B),
    .opcode(opcode),
    .result(result),
    .carry(carry),
    .zero(zero)
);

initial begin

    $dumpfile("alu.vcd");
    $dumpvars(0, alu_tb);

    // ADD
    A = 8'd10;
    B = 8'd5;
    opcode = 3'b000;
    #10;

    // SUB
    A = 8'd10;
    B = 8'd5;
    opcode = 3'b001;
    #10;

    // AND
    A = 8'b10101010;
    B = 8'b11001100;
    opcode = 3'b010;
    #10;

    // OR
    opcode = 3'b011;
    #10;

    // XOR
    opcode = 3'b100;
    #10;

    // NOT
    opcode = 3'b101;
    #10;

    // SHIFT LEFT
    A = 8'b00001111;
    opcode = 3'b110;
    #10;

    // SHIFT RIGHT
    A = 8'b11110000;
    opcode = 3'b111;
    #10;

    $finish;

end

endmodule

alu.vcd
$date
	Sun Aug  9 00:27:02 2026
$end
$version
	Icarus Verilog
$end
$timescale
	1ps
$end
$scope module alu_tb $end
$var wire 1 ! zero $end
$var wire 8 " result [7:0] $end
$var wire 1 # carry $end
$var reg 8 $ A [7:0] $end
$var reg 8 % B [7:0] $end
$var reg 3 & opcode [2:0] $end
$scope module uut $end
$var wire 8 ' A [7:0] $end
$var wire 8 ( B [7:0] $end
$var wire 3 ) opcode [2:0] $end
$var wire 1 ! zero $end
$var reg 1 # carry $end
$var reg 8 * result [7:0] $end
$upscope $end
$upscope $end
$enddefinitions $end
$comment Show the parameter values. $end
$dumpall
$end
#0
$dumpvars
b1111 *
b0 )
b101 (
b1010 '
b0 &
b101 %
b1010 $
0#
b1111 "
0!
$end
#10000
0!
b101 "
b101 *
b1 &
b1 )
#20000
0!
b10001000 "
b10001000 *
b10 &
b10 )
b11001100 %
b11001100 (
b10101010 $
b10101010 '
#30000
0!
b11101110 "
b11101110 *
b11 &
b11 )
#40000
0!
b1100110 "
b1100110 *
b100 &
b100 )
#50000
0!
b1010101 "
b1010101 *
b101 &
b101 )
#60000
0!
b11110 "
b11110 *
b110 &
b110 )
b1111 $
b1111 '
#70000
0!
b1111000 "
b1111000 *
b111 &
b111 )
b11110000 $
b11110000 '
